eb_model/__init__.py
eb_model/cli/__init__.py
eb_model/cli/bswm_xdm_2_xls_cli.py
eb_model/cli/ecuc_xdm_2_xls_cli.py
eb_model/cli/nvm_xdm_2_xls_cli.py
eb_model/cli/os_xdm_2_xls_cli.py
eb_model/cli/pref_system_importer_cli.py
eb_model/cli/rte_xdm_2_xls_cli.py
eb_model/models/__init__.py
eb_model/models/abstract.py
eb_model/models/bswm_xdm.py
eb_model/models/eb_doc.py
eb_model/models/eclipse_project.py
eb_model/models/ecuc_xdm.py
eb_model/models/importer_xdm.py
eb_model/models/nvm_xdm.py
eb_model/models/os_xdm.py
eb_model/models/rte_xdm.py
eb_model/parser/__init__.py
eb_model/parser/bswm_xdm_parser.py
eb_model/parser/eb_parser.py
eb_model/parser/eb_parser_factory.py
eb_model/parser/ecuc_xdm_parser.py
eb_model/parser/nvm_xdm_parser.py
eb_model/parser/os_xdm_parser.py
eb_model/parser/pref_xdm_parser.py
eb_model/parser/rte_xdm_parser.py
eb_model/reporter/__init__.py
eb_model/reporter/markdown.py
eb_model/reporter/excel_reporter/__init__.py
eb_model/reporter/excel_reporter/abstract.py
eb_model/reporter/excel_reporter/bswm_xdm.py
eb_model/reporter/excel_reporter/ecuc_xdm.py
eb_model/reporter/excel_reporter/nvm_xdm.py
eb_model/reporter/excel_reporter/os_xdm.py
eb_model/reporter/excel_reporter/rte_xdm.py
eb_model/tests/__init__.py
eb_model/tests/models/__init__.py
eb_model/tests/models/test_abstract.py
eb_model/tests/models/test_eb_doc.py
eb_model/tests/models/test_eb_model.py
eb_model/tests/models/test_eclipse_project.py
eb_model/tests/models/test_ecuc_container.py
eb_model/tests/models/test_importer_xdm.py
eb_model/tests/parser/__init__.py
eb_model/tests/parser/test_ecuc_xdm_parser.py
eb_model/tests/parser/test_nvm_xdm_parser.py
eb_model/tests/parser/test_os_xdm_parser.py
eb_model/writer/__init__.py
eb_model/writer/project_writer.py
eb_model/writer/text_writer.py
py_eb_model-1.2.3.dist-info/LICENSE
py_eb_model-1.2.3.dist-info/METADATA
py_eb_model-1.2.3.dist-info/WHEEL
py_eb_model-1.2.3.dist-info/entry_points.txt
py_eb_model-1.2.3.dist-info/top_level.txt
py_eb_model-1.2.3.dist-info/RECORD
