Metadata-Version: 2.1
Name: py-eb-model
Version: 1.2.3
Summary: The parser for EB XDM file
Home-page: UNKNOWN
Author: melodypapa
Author-email: melodypapa@outlook.com
License: proprietary
Keywords: EB Tresos XDM
Platform: UNKNOWN
Classifier: Development Status :: 1 - Planning
Classifier: Environment :: Console
Classifier: Programming Language :: Python :: 3
Classifier: License :: OSI Approved :: MIT License
Classifier: Operating System :: OS Independent
Requires-Dist: openpyxl
Provides-Extra: pytest
Requires-Dist: pytest-cov ; extra == 'pytest'
